{
    "filePath": "/new_df.csv",
    "aggregatorFunction": null,
    "aggregatorColumn": null,
    "columnFilters": [
        {
            "column": "team_name",
            "operator": "equals",
            "value": "Brighton",
            "condition": "or"
        },
        {
            "column": "team_code",
            "operator": "equals",
            "value": "3",
            "condition": ""
        }
    ],
    "displayColumns": [
        "team_name", "team_code"
    ],
    "distinctCols": [
        "team_name"
    ],
    "groupedBy": [
    ]
}